SimpleVFX/SimpleVFX.py
SimpleVFX/__about__.py
SimpleVFX/__init__.py
SimpleVFX/example.py
SimpleVFX/example/example.png
simplevfx-0.0.2.dist-info/METADATA
simplevfx-0.0.2.dist-info/WHEEL
simplevfx-0.0.2.dist-info/licenses/LICENSE
simplevfx-0.0.2.dist-info/RECORD
